DaimaNengYouDuonanJiandanDeWangyeDaimaShu/README.md
DaimaNengYouDuonanJiandanDeWangyeDaimaShu/__init__.py
DaimaNengYouDuonanJiandanDeWangyeDaimaShu/__main__.py
DaimaNengYouDuonanJiandanDeWangyeDaimaShu/file.epub
DaimaNengYouDuonanJiandanDeWangyeDaimaShu/index.html
DaimaNengYouDuonanJiandanDeWangyeDaimaShu/css/__init__.py
DaimaNengYouDuonanJiandanDeWangyeDaimaShu/css/annotations.css
DaimaNengYouDuonanJiandanDeWangyeDaimaShu/css/main.css
DaimaNengYouDuonanJiandanDeWangyeDaimaShu/css/normalize.css
DaimaNengYouDuonanJiandanDeWangyeDaimaShu/css/popup.css
DaimaNengYouDuonanJiandanDeWangyeDaimaShu/font/__init__.py
DaimaNengYouDuonanJiandanDeWangyeDaimaShu/font/fontello.eot
DaimaNengYouDuonanJiandanDeWangyeDaimaShu/font/fontello.svg
DaimaNengYouDuonanJiandanDeWangyeDaimaShu/font/fontello.ttf
DaimaNengYouDuonanJiandanDeWangyeDaimaShu/font/fontello.woff
DaimaNengYouDuonanJiandanDeWangyeDaimaShu/img/__init__.py
DaimaNengYouDuonanJiandanDeWangyeDaimaShu/img/annotator-glyph-sprite.png
DaimaNengYouDuonanJiandanDeWangyeDaimaShu/img/annotator-icon-sprite.png
DaimaNengYouDuonanJiandanDeWangyeDaimaShu/img/apple-touch-icon.png
DaimaNengYouDuonanJiandanDeWangyeDaimaShu/img/cancelfullscreen.png
DaimaNengYouDuonanJiandanDeWangyeDaimaShu/img/close.png
DaimaNengYouDuonanJiandanDeWangyeDaimaShu/img/fullscreen.png
DaimaNengYouDuonanJiandanDeWangyeDaimaShu/img/loader.gif
DaimaNengYouDuonanJiandanDeWangyeDaimaShu/img/menu-icon.png
DaimaNengYouDuonanJiandanDeWangyeDaimaShu/img/save.png
DaimaNengYouDuonanJiandanDeWangyeDaimaShu/img/saved.png
DaimaNengYouDuonanJiandanDeWangyeDaimaShu/img/settings-s.png
DaimaNengYouDuonanJiandanDeWangyeDaimaShu/img/settings.png
DaimaNengYouDuonanJiandanDeWangyeDaimaShu/img/star.png
DaimaNengYouDuonanJiandanDeWangyeDaimaShu/js/__init__.py
DaimaNengYouDuonanJiandanDeWangyeDaimaShu/js/epub.js
DaimaNengYouDuonanJiandanDeWangyeDaimaShu/js/epub.min.js
DaimaNengYouDuonanJiandanDeWangyeDaimaShu/js/epub.min.map
DaimaNengYouDuonanJiandanDeWangyeDaimaShu/js/hooks.min.js
daima_neng_you_duonan_jiandan_de_wangye_daima_shu-2024.3.2.0.dist-info/METADATA
daima_neng_you_duonan_jiandan_de_wangye_daima_shu-2024.3.2.0.dist-info/WHEEL
daima_neng_you_duonan_jiandan_de_wangye_daima_shu-2024.3.2.0.dist-info/entry_points.txt
daima_neng_you_duonan_jiandan_de_wangye_daima_shu-2024.3.2.0.dist-info/top_level.txt
daima_neng_you_duonan_jiandan_de_wangye_daima_shu-2024.3.2.0.dist-info/RECORD
